<?xml version="1.0" encoding="utf-8" ?>
<dwsync>
<file name="fullcalendar.css" server="ftp.thesewingshed.ie/public_html/testing_pri/" local="131453861152533785" remote="131447143800000000" Dst="2" />
<file name="fullcalendar.min.css" server="ftp.thesewingshed.ie/public_html/testing_pri/" local="131453861160005272" remote="131447143800000000" Dst="2" />
<file name="fullcalendar.min.js" server="ftp.thesewingshed.ie/public_html/testing_pri/" local="131453861168948562" remote="131447143800000000" Dst="2" />
<file name="fullcalendar.js" server="ftp.thesewingshed.ie/public_html/testing_pri/" local="131453861174639316" remote="131447143800000000" Dst="2" />
<file name="fullcalendar.print.min.css" server="ftp.thesewingshed.ie/public_html/testing_pri/" local="131453861175349834" remote="131447143800000000" Dst="2" />
<file name="gcal.html" server="ftp.thesewingshed.ie/public_html/testing_pri/" local="131453861178283084" remote="131447143800000000" Dst="2" />
<file name="gcal.js" server="ftp.thesewingshed.ie/public_html/testing_pri/" local="131453861179539746" remote="131447143800000000" Dst="2" />
<file name="gcal.min.js" server="ftp.thesewingshed.ie/public_html/testing_pri/" local="131453861181516136" remote="131447143800000000" Dst="2" />
<file name="locale-all.js" server="ftp.thesewingshed.ie/public_html/testing_pri/" local="131453861344352259" remote="131447143800000000" Dst="2" />
<file name="sewingshed.js" server="ftp.thesewingshed.ie/public_html/testing_pri/" local="131453861345662637" remote="131447143800000000" Dst="2" />
<file name="fullcalendar.css" server="C:/xampp/htdocs/sew.ie/" local="131453861152533785" remote="131453861150000000" Dst="2" />
<file name="fullcalendar.js" server="C:/xampp/htdocs/sew.ie/" local="131453861174639316" remote="131453861170000000" Dst="2" />
<file name="fullcalendar.min.css" server="C:/xampp/htdocs/sew.ie/" local="131453861160005272" remote="131453861160000000" Dst="2" />
<file name="fullcalendar.min.js" server="C:/xampp/htdocs/sew.ie/" local="131453861168948562" remote="131453861160000000" Dst="2" />
<file name="fullcalendar.print.min.css" server="C:/xampp/htdocs/sew.ie/" local="131453861175349834" remote="131453861170000000" Dst="2" />
<file name="gcal.html" server="C:/xampp/htdocs/sew.ie/" local="131453861178283084" remote="131453861170000000" Dst="2" />
<file name="gcal.js" server="C:/xampp/htdocs/sew.ie/" local="131453861179539746" remote="131453861170000000" Dst="2" />
<file name="gcal.min.js" server="C:/xampp/htdocs/sew.ie/" local="131453861181516136" remote="131453861180000000" Dst="2" />
<file name="locale-all.js" server="C:/xampp/htdocs/sew.ie/" local="131453861344352259" remote="131453861340000000" Dst="2" />
<file name="sewingshed.js" server="C:/xampp/htdocs/sew.ie/" local="131453861345662637" remote="131453861340000000" Dst="2" />
<file name="fullcalendar.css" server="ftp.thesewingshed.ie//public_html/testing/" local="131453861152533785" remote="131455516800000000" Dst="2" />
<file name="fullcalendar.js" server="ftp.thesewingshed.ie//public_html/testing/" local="131453861174639316" remote="131455516800000000" Dst="2" />
<file name="fullcalendar.min.css" server="ftp.thesewingshed.ie//public_html/testing/" local="131453861160005272" remote="131455516800000000" Dst="2" />
<file name="fullcalendar.min.js" server="ftp.thesewingshed.ie//public_html/testing/" local="131453861168948562" remote="131455516800000000" Dst="2" />
<file name="fullcalendar.print.min.css" server="ftp.thesewingshed.ie//public_html/testing/" local="131453861175349834" remote="131455516800000000" Dst="2" />
<file name="gcal.html" server="ftp.thesewingshed.ie//public_html/testing/" local="131453861178283084" remote="131455516800000000" Dst="2" />
<file name="gcal.js" server="ftp.thesewingshed.ie//public_html/testing/" local="131453861179539746" remote="131455516800000000" Dst="2" />
<file name="gcal.min.js" server="ftp.thesewingshed.ie//public_html/testing/" local="131453861181516136" remote="131455516800000000" Dst="2" />
<file name="locale-all.js" server="ftp.thesewingshed.ie//public_html/testing/" local="131453861344352259" remote="131455516800000000" Dst="2" />
<file name="sewingshed.js" server="ftp.thesewingshed.ie//public_html/testing/" local="131453861345662637" remote="131455516800000000" Dst="2" />
</dwsync>